CHANGELOG.rst
LICENSE
MANIFEST.in
README.rst
setup.py
django_oss_storage/__init__.py
django_oss_storage/backends.py
django_oss_storage/defaults.py
django_oss_storage.egg-info/PKG-INFO
django_oss_storage.egg-info/SOURCES.txt
django_oss_storage.egg-info/dependency_links.txt
django_oss_storage.egg-info/requires.txt
django_oss_storage.egg-info/top_level.txt
tests/manage.py
tests/django-oss-storage-test/__init__.py
tests/django-oss-storage-test/settings.py
tests/django-oss-storage-test/tests.py